aliyunsdkdg/__init__.py
aliyunsdkdg/endpoint.py
aliyunsdkdg/request/__init__.py
aliyunsdkdg/request/v20190327/AddDatabaseListRequest.py
aliyunsdkdg/request/v20190327/AddDatabaseRequest.py
aliyunsdkdg/request/v20190327/ConnectDatabaseRequest.py
aliyunsdkdg/request/v20190327/CreateDatabaseAccessPointRequest.py
aliyunsdkdg/request/v20190327/CreateGatewayRequest.py
aliyunsdkdg/request/v20190327/CreateGatewayVerifyCodeRequest.py
aliyunsdkdg/request/v20190327/DeleteDatabaseAccessPointRequest.py
aliyunsdkdg/request/v20190327/DeleteDatabaseRequest.py
aliyunsdkdg/request/v20190327/DeleteGatewayInstanceRequest.py
aliyunsdkdg/request/v20190327/DeleteGatewayRequest.py
aliyunsdkdg/request/v20190327/DescribeRegionsRequest.py
aliyunsdkdg/request/v20190327/DownloadGatewayProgramRequest.py
aliyunsdkdg/request/v20190327/FindUserGatewayByIdRequest.py
aliyunsdkdg/request/v20190327/GetUserDatabasesRequest.py
aliyunsdkdg/request/v20190327/GetUserGatewayInstancesRequest.py
aliyunsdkdg/request/v20190327/GetUserGatewaysRequest.py
aliyunsdkdg/request/v20190327/ListDatabaseAccessPointRequest.py
aliyunsdkdg/request/v20190327/ModifyDatabaseRequest.py
aliyunsdkdg/request/v20190327/ModifyGatewayRequest.py
aliyunsdkdg/request/v20190327/RetryDatabaseRequest.py
aliyunsdkdg/request/v20190327/StopGatewayRequest.py
aliyunsdkdg/request/v20190327/__init__.py
aliyun_python_sdk_dg-1.0.10.dist-info/LICENSE
aliyun_python_sdk_dg-1.0.10.dist-info/METADATA
aliyun_python_sdk_dg-1.0.10.dist-info/WHEEL
aliyun_python_sdk_dg-1.0.10.dist-info/top_level.txt
aliyun_python_sdk_dg-1.0.10.dist-info/RECORD
